outlook_event_slack_notification_bot/__init__.py
outlook_event_slack_notification_bot/model.py
outlook_event_slack_notification_bot/outlook_calendar.py
outlook_event_slack_notification_bot/slack.py
outlook_event_slack_bot-0.0.8.dist-info/LICENSE
outlook_event_slack_bot-0.0.8.dist-info/METADATA
outlook_event_slack_bot-0.0.8.dist-info/WHEEL
outlook_event_slack_bot-0.0.8.dist-info/top_level.txt
outlook_event_slack_bot-0.0.8.dist-info/RECORD
