Metadata-Version: 2.1
Name: outlook-event-slack-bot
Version: 0.0.8
Summary: A Microsoft Outlook event Slack bot
Home-page: https://github.com/ZPascal/ms_outlook_event_slack_bot
Author: Pascal Zimmermann
Author-email: info@theiotstudio.com
Project-URL: Source, https://github.com/ZPascal/ms_outlook_event_slack_bot
Project-URL: Bug Tracker, https://github.com/ZPascal/ms_outlook_event_slack_bot/issues
Project-URL: Documentation, https://zpascal.github.io/ms_outlook_event_slack_bot/
Classifier: Programming Language :: Python :: 3
Classifier: License :: OSI Approved
Classifier: Operating System :: OS Independent
Requires-Python: >=3.8
License-File: LICENSE
Requires-Dist: httpx[http2]
Requires-Dist: msal
